tf2ss/__init__.py
tf2ss/base.py
tf2ss/test_tf2ss.py
tf2ss/tf2ss_report.md
tf2ss/timeresp.py
tf2ss-1.2.0.dist-info/METADATA
tf2ss-1.2.0.dist-info/WHEEL
tf2ss-1.2.0.dist-info/licenses/LICENSE
tf2ss-1.2.0.dist-info/RECORD
