Metadata-Version: 2.4
Name: tf2ss
Version: 1.2.0
Summary: Transfer Function to State Space conversion for MIMO systems
Project-URL: repository, https://github.com/MarekWadinger/tf2ss
Project-URL: documentation, https://github.com/MarekWadinger/tf2ss#readme
Project-URL: issues, https://github.com/MarekWadinger/tf2ss/issues
Author-email: Marek Wadinger <marek.wadinger@example.com>
License: MIT
License-File: LICENSE
Keywords: MIMO,control systems,state space,system identification,transfer function
Classifier: Development Status :: 4 - Beta
Classifier: Intended Audience :: Education
Classifier: Intended Audience :: Science/Research
Classifier: License :: OSI Approved :: MIT License
Classifier: Programming Language :: Python :: 3
Classifier: Programming Language :: Python :: 3.10
Classifier: Programming Language :: Python :: 3.11
Classifier: Programming Language :: Python :: 3.12
Classifier: Topic :: Scientific/Engineering
Classifier: Topic :: Scientific/Engineering :: Mathematics
Requires-Python: >=3.10
Requires-Dist: control<1.0.0,>=0.9.0
Requires-Dist: numpy<3.0.0,>=1.20.0
Requires-Dist: scipy<2.0.0,>=1.7.0
Requires-Dist: sympy<2.0.0,>=1.8
Provides-Extra: benchmark
Requires-Dist: slycot>=0.6.0; extra == 'benchmark'
Provides-Extra: dev
Requires-Dist: commitizen>=4.0.0; extra == 'dev'
Requires-Dist: mypy>=1.0.0; extra == 'dev'
Requires-Dist: pre-commit>=3.0.0; extra == 'dev'
Requires-Dist: ruff>=0.1.0; extra == 'dev'
Provides-Extra: test
Requires-Dist: pytest-cov>=4.0.0; extra == 'test'
Requires-Dist: pytest>=7.0.0; extra == 'test'
